jbrowse_jupyter/__init__.py
jbrowse_jupyter/jbrowse_config.py
jbrowse_jupyter/tracks.py
jbrowse_jupyter/util.py
jbrowse_jupyter-1.5.9.dist-info/LICENSE
jbrowse_jupyter-1.5.9.dist-info/METADATA
jbrowse_jupyter-1.5.9.dist-info/WHEEL
jbrowse_jupyter-1.5.9.dist-info/top_level.txt
jbrowse_jupyter-1.5.9.dist-info/RECORD
