Metadata-Version: 2.1
Name: jbrowse-jupyter
Version: 1.5.9
Summary: Jupyter Notebooks extension for showing JBrowse views
Home-page: https://github.com/GMOD/jbrowse-jupyter
Author: Teresa De Jesus Martinez
Author-email: tere486martinez@gmail.com
Maintainer: Teresa De Jesus Martinez; JBrowse Team
Maintainer-email: tere486martinez@gmail.com
License: Apache-2.0
Project-URL: Bug Tracker, https://github.com/GMOD/jbrowse-jupyter/issues
Classifier: Programming Language :: Python :: 3
Classifier: Topic :: Scientific/Engineering
Classifier: Intended Audience :: Science/Research
Classifier: Topic :: Scientific/Engineering :: Bio-Informatics
Requires-Python: >=3.6
License-File: LICENSE
Requires-Dist: dash >=2.11.1
Requires-Dist: dash-jbrowse >=1.2.0
Requires-Dist: pandas >=1.1.5
Requires-Dist: IPython >=7.0.0
